{
  "openapi": "3.0.4",
  "info": {
    "title": "ActivProformaAPI",
    "version": "1.0"
  },
  "paths": {
    "/api/Articles": {
      "get": {
        "tags": [
          "Articles"
        ],
        "responses": {
          "200": {
            "description": "OK",
            "content": {
              "text/plain": {
                "schema": {
                  "type": "array",
                  "items": {
                    "$ref": "#/components/schemas/Article"
                  }
                }
              },
              "application/json": {
                "schema": {
                  "type": "array",
                  "items": {
                    "$ref": "#/components/schemas/Article"
                  }
                }
              },
              "text/json": {
                "schema": {
                  "type": "array",
                  "items": {
                    "$ref": "#/components/schemas/Article"
                  }
                }
              }
            }
          }
        }
      },
      "post": {
        "tags": [
          "Articles"
        ],
        "requestBody": {
          "content": {
            "application/json": {
              "schema": {
                "$ref": "#/components/schemas/Article"
              }
            },
            "text/json": {
              "schema": {
                "$ref": "#/components/schemas/Article"
              }
            },
            "application/*+json": {
              "schema": {
                "$ref": "#/components/schemas/Article"
              }
            }
          }
        },
        "responses": {
          "200": {
            "description": "OK",
            "content": {
              "text/plain": {
                "schema": {
                  "$ref": "#/components/schemas/Article"
                }
              },
              "application/json": {
                "schema": {
                  "$ref": "#/components/schemas/Article"
                }
              },
              "text/json": {
                "schema": {
                  "$ref": "#/components/schemas/Article"
                }
              }
            }
          }
        }
      }
    },
    "/api/Articles/{id}": {
      "get": {
        "tags": [
          "Articles"
        ],
        "parameters": [
          {
            "name": "id",
            "in": "path",
            "required": true,
            "schema": {
              "type": "integer",
              "format": "int32"
            }
          }
        ],
        "responses": {
          "200": {
            "description": "OK",
            "content": {
              "text/plain": {
                "schema": {
                  "$ref": "#/components/schemas/Article"
                }
              },
              "application/json": {
                "schema": {
                  "$ref": "#/components/schemas/Article"
                }
              },
              "text/json": {
                "schema": {
                  "$ref": "#/components/schemas/Article"
                }
              }
            }
          }
        }
      },
      "put": {
        "tags": [
          "Articles"
        ],
        "parameters": [
          {
            "name": "id",
            "in": "path",
            "required": true,
            "schema": {
              "type": "integer",
              "format": "int32"
            }
          }
        ],
        "requestBody": {
          "content": {
            "application/json": {
              "schema": {
                "$ref": "#/components/schemas/Article"
              }
            },
            "text/json": {
              "schema": {
                "$ref": "#/components/schemas/Article"
              }
            },
            "application/*+json": {
              "schema": {
                "$ref": "#/components/schemas/Article"
              }
            }
          }
        },
        "responses": {
          "200": {
            "description": "OK"
          }
        }
      },
      "delete": {
        "tags": [
          "Articles"
        ],
        "parameters": [
          {
            "name": "id",
            "in": "path",
            "required": true,
            "schema": {
              "type": "integer",
              "format": "int32"
            }
          }
        ],
        "responses": {
          "200": {
            "description": "OK"
          }
        }
      }
    },
    "/api/Clients": {
      "get": {
        "tags": [
          "Clients"
        ],
        "responses": {
          "200": {
            "description": "OK",
            "content": {
              "text/plain": {
                "schema": {
                  "type": "array",
                  "items": {
                    "$ref": "#/components/schemas/Client"
                  }
                }
              },
              "application/json": {
                "schema": {
                  "type": "array",
                  "items": {
                    "$ref": "#/components/schemas/Client"
                  }
                }
              },
              "text/json": {
                "schema": {
                  "type": "array",
                  "items": {
                    "$ref": "#/components/schemas/Client"
                  }
                }
              }
            }
          }
        }
      },
      "post": {
        "tags": [
          "Clients"
        ],
        "requestBody": {
          "content": {
            "application/json": {
              "schema": {
                "$ref": "#/components/schemas/Client"
              }
            },
            "text/json": {
              "schema": {
                "$ref": "#/components/schemas/Client"
              }
            },
            "application/*+json": {
              "schema": {
                "$ref": "#/components/schemas/Client"
              }
            }
          }
        },
        "responses": {
          "200": {
            "description": "OK",
            "content": {
              "text/plain": {
                "schema": {
                  "$ref": "#/components/schemas/Client"
                }
              },
              "application/json": {
                "schema": {
                  "$ref": "#/components/schemas/Client"
                }
              },
              "text/json": {
                "schema": {
                  "$ref": "#/components/schemas/Client"
                }
              }
            }
          }
        }
      }
    },
    "/api/Clients/{id}": {
      "get": {
        "tags": [
          "Clients"
        ],
        "parameters": [
          {
            "name": "id",
            "in": "path",
            "required": true,
            "schema": {
              "type": "integer",
              "format": "int32"
            }
          }
        ],
        "responses": {
          "200": {
            "description": "OK",
            "content": {
              "text/plain": {
                "schema": {
                  "$ref": "#/components/schemas/Client"
                }
              },
              "application/json": {
                "schema": {
                  "$ref": "#/components/schemas/Client"
                }
              },
              "text/json": {
                "schema": {
                  "$ref": "#/components/schemas/Client"
                }
              }
            }
          }
        }
      },
      "put": {
        "tags": [
          "Clients"
        ],
        "parameters": [
          {
            "name": "id",
            "in": "path",
            "required": true,
            "schema": {
              "type": "integer",
              "format": "int32"
            }
          }
        ],
        "requestBody": {
          "content": {
            "application/json": {
              "schema": {
                "$ref": "#/components/schemas/Client"
              }
            },
            "text/json": {
              "schema": {
                "$ref": "#/components/schemas/Client"
              }
            },
            "application/*+json": {
              "schema": {
                "$ref": "#/components/schemas/Client"
              }
            }
          }
        },
        "responses": {
          "200": {
            "description": "OK"
          }
        }
      },
      "delete": {
        "tags": [
          "Clients"
        ],
        "parameters": [
          {
            "name": "id",
            "in": "path",
            "required": true,
            "schema": {
              "type": "integer",
              "format": "int32"
            }
          }
        ],
        "responses": {
          "200": {
            "description": "OK"
          }
        }
      }
    },
    "/api/Commandes": {
      "get": {
        "tags": [
          "Commandes"
        ],
        "responses": {
          "200": {
            "description": "OK",
            "content": {
              "text/plain": {
                "schema": {
                  "type": "array",
                  "items": {
                    "$ref": "#/components/schemas/Commande"
                  }
                }
              },
              "application/json": {
                "schema": {
                  "type": "array",
                  "items": {
                    "$ref": "#/components/schemas/Commande"
                  }
                }
              },
              "text/json": {
                "schema": {
                  "type": "array",
                  "items": {
                    "$ref": "#/components/schemas/Commande"
                  }
                }
              }
            }
          }
        }
      },
      "post": {
        "tags": [
          "Commandes"
        ],
        "requestBody": {
          "content": {
            "application/json": {
              "schema": {
                "$ref": "#/components/schemas/Commande"
              }
            },
            "text/json": {
              "schema": {
                "$ref": "#/components/schemas/Commande"
              }
            },
            "application/*+json": {
              "schema": {
                "$ref": "#/components/schemas/Commande"
              }
            }
          }
        },
        "responses": {
          "200": {
            "description": "OK",
            "content": {
              "text/plain": {
                "schema": {
                  "$ref": "#/components/schemas/Commande"
                }
              },
              "application/json": {
                "schema": {
                  "$ref": "#/components/schemas/Commande"
                }
              },
              "text/json": {
                "schema": {
                  "$ref": "#/components/schemas/Commande"
                }
              }
            }
          }
        }
      }
    },
    "/api/Commandes/{id}": {
      "get": {
        "tags": [
          "Commandes"
        ],
        "parameters": [
          {
            "name": "id",
            "in": "path",
            "required": true,
            "schema": {
              "type": "integer",
              "format": "int32"
            }
          }
        ],
        "responses": {
          "200": {
            "description": "OK",
            "content": {
              "text/plain": {
                "schema": {
                  "$ref": "#/components/schemas/Commande"
                }
              },
              "application/json": {
                "schema": {
                  "$ref": "#/components/schemas/Commande"
                }
              },
              "text/json": {
                "schema": {
                  "$ref": "#/components/schemas/Commande"
                }
              }
            }
          }
        }
      },
      "put": {
        "tags": [
          "Commandes"
        ],
        "parameters": [
          {
            "name": "id",
            "in": "path",
            "required": true,
            "schema": {
              "type": "integer",
              "format": "int32"
            }
          }
        ],
        "requestBody": {
          "content": {
            "application/json": {
              "schema": {
                "$ref": "#/components/schemas/Commande"
              }
            },
            "text/json": {
              "schema": {
                "$ref": "#/components/schemas/Commande"
              }
            },
            "application/*+json": {
              "schema": {
                "$ref": "#/components/schemas/Commande"
              }
            }
          }
        },
        "responses": {
          "200": {
            "description": "OK"
          }
        }
      },
      "delete": {
        "tags": [
          "Commandes"
        ],
        "parameters": [
          {
            "name": "id",
            "in": "path",
            "required": true,
            "schema": {
              "type": "integer",
              "format": "int32"
            }
          }
        ],
        "responses": {
          "200": {
            "description": "OK"
          }
        }
      }
    },
    "/api/Commandes/client/{idClient}": {
      "get": {
        "tags": [
          "Commandes"
        ],
        "parameters": [
          {
            "name": "idClient",
            "in": "path",
            "required": true,
            "schema": {
              "type": "integer",
              "format": "int32"
            }
          }
        ],
        "responses": {
          "200": {
            "description": "OK",
            "content": {
              "text/plain": {
                "schema": {
                  "type": "array",
                  "items": {
                    "$ref": "#/components/schemas/Commande"
                  }
                }
              },
              "application/json": {
                "schema": {
                  "type": "array",
                  "items": {
                    "$ref": "#/components/schemas/Commande"
                  }
                }
              },
              "text/json": {
                "schema": {
                  "type": "array",
                  "items": {
                    "$ref": "#/components/schemas/Commande"
                  }
                }
              }
            }
          }
        }
      }
    },
    "/api/Details": {
      "get": {
        "tags": [
          "Details"
        ],
        "responses": {
          "200": {
            "description": "OK",
            "content": {
              "text/plain": {
                "schema": {
                  "type": "array",
                  "items": {
                    "$ref": "#/components/schemas/Detail"
                  }
                }
              },
              "application/json": {
                "schema": {
                  "type": "array",
                  "items": {
                    "$ref": "#/components/schemas/Detail"
                  }
                }
              },
              "text/json": {
                "schema": {
                  "type": "array",
                  "items": {
                    "$ref": "#/components/schemas/Detail"
                  }
                }
              }
            }
          }
        }
      },
      "post": {
        "tags": [
          "Details"
        ],
        "requestBody": {
          "content": {
            "application/json": {
              "schema": {
                "$ref": "#/components/schemas/Detail"
              }
            },
            "text/json": {
              "schema": {
                "$ref": "#/components/schemas/Detail"
              }
            },
            "application/*+json": {
              "schema": {
                "$ref": "#/components/schemas/Detail"
              }
            }
          }
        },
        "responses": {
          "200": {
            "description": "OK",
            "content": {
              "text/plain": {
                "schema": {
                  "$ref": "#/components/schemas/Detail"
                }
              },
              "application/json": {
                "schema": {
                  "$ref": "#/components/schemas/Detail"
                }
              },
              "text/json": {
                "schema": {
                  "$ref": "#/components/schemas/Detail"
                }
              }
            }
          }
        }
      }
    },
    "/api/Details/{id}": {
      "get": {
        "tags": [
          "Details"
        ],
        "parameters": [
          {
            "name": "id",
            "in": "path",
            "required": true,
            "schema": {
              "type": "integer",
              "format": "int32"
            }
          }
        ],
        "responses": {
          "200": {
            "description": "OK",
            "content": {
              "text/plain": {
                "schema": {
                  "$ref": "#/components/schemas/Detail"
                }
              },
              "application/json": {
                "schema": {
                  "$ref": "#/components/schemas/Detail"
                }
              },
              "text/json": {
                "schema": {
                  "$ref": "#/components/schemas/Detail"
                }
              }
            }
          }
        }
      },
      "put": {
        "tags": [
          "Details"
        ],
        "parameters": [
          {
            "name": "id",
            "in": "path",
            "required": true,
            "schema": {
              "type": "integer",
              "format": "int32"
            }
          }
        ],
        "requestBody": {
          "content": {
            "application/json": {
              "schema": {
                "$ref": "#/components/schemas/Detail"
              }
            },
            "text/json": {
              "schema": {
                "$ref": "#/components/schemas/Detail"
              }
            },
            "application/*+json": {
              "schema": {
                "$ref": "#/components/schemas/Detail"
              }
            }
          }
        },
        "responses": {
          "200": {
            "description": "OK"
          }
        }
      },
      "delete": {
        "tags": [
          "Details"
        ],
        "parameters": [
          {
            "name": "id",
            "in": "path",
            "required": true,
            "schema": {
              "type": "integer",
              "format": "int32"
            }
          }
        ],
        "responses": {
          "200": {
            "description": "OK"
          }
        }
      }
    },
    "/api/Details/commande/{idCommande}": {
      "get": {
        "tags": [
          "Details"
        ],
        "parameters": [
          {
            "name": "idCommande",
            "in": "path",
            "required": true,
            "schema": {
              "type": "integer",
              "format": "int32"
            }
          }
        ],
        "responses": {
          "200": {
            "description": "OK",
            "content": {
              "text/plain": {
                "schema": {
                  "type": "array",
                  "items": {
                    "$ref": "#/components/schemas/Detail"
                  }
                }
              },
              "application/json": {
                "schema": {
                  "type": "array",
                  "items": {
                    "$ref": "#/components/schemas/Detail"
                  }
                }
              },
              "text/json": {
                "schema": {
                  "type": "array",
                  "items": {
                    "$ref": "#/components/schemas/Detail"
                  }
                }
              }
            }
          }
        }
      }
    },
    "/api/LigneravitaillementArticles": {
      "get": {
        "tags": [
          "LigneravitaillementArticles"
        ],
        "responses": {
          "200": {
            "description": "OK",
            "content": {
              "text/plain": {
                "schema": {
                  "type": "array",
                  "items": {
                    "$ref": "#/components/schemas/LigneravitaillementArticle"
                  }
                }
              },
              "application/json": {
                "schema": {
                  "type": "array",
                  "items": {
                    "$ref": "#/components/schemas/LigneravitaillementArticle"
                  }
                }
              },
              "text/json": {
                "schema": {
                  "type": "array",
                  "items": {
                    "$ref": "#/components/schemas/LigneravitaillementArticle"
                  }
                }
              }
            }
          }
        }
      },
      "post": {
        "tags": [
          "LigneravitaillementArticles"
        ],
        "requestBody": {
          "content": {
            "application/json": {
              "schema": {
                "$ref": "#/components/schemas/LigneravitaillementArticle"
              }
            },
            "text/json": {
              "schema": {
                "$ref": "#/components/schemas/LigneravitaillementArticle"
              }
            },
            "application/*+json": {
              "schema": {
                "$ref": "#/components/schemas/LigneravitaillementArticle"
              }
            }
          }
        },
        "responses": {
          "200": {
            "description": "OK",
            "content": {
              "text/plain": {
                "schema": {
                  "$ref": "#/components/schemas/LigneravitaillementArticle"
                }
              },
              "application/json": {
                "schema": {
                  "$ref": "#/components/schemas/LigneravitaillementArticle"
                }
              },
              "text/json": {
                "schema": {
                  "$ref": "#/components/schemas/LigneravitaillementArticle"
                }
              }
            }
          }
        }
      }
    },
    "/api/LigneravitaillementArticles/{id}": {
      "get": {
        "tags": [
          "LigneravitaillementArticles"
        ],
        "parameters": [
          {
            "name": "id",
            "in": "path",
            "required": true,
            "schema": {
              "type": "integer",
              "format": "int32"
            }
          }
        ],
        "responses": {
          "200": {
            "description": "OK",
            "content": {
              "text/plain": {
                "schema": {
                  "$ref": "#/components/schemas/LigneravitaillementArticle"
                }
              },
              "application/json": {
                "schema": {
                  "$ref": "#/components/schemas/LigneravitaillementArticle"
                }
              },
              "text/json": {
                "schema": {
                  "$ref": "#/components/schemas/LigneravitaillementArticle"
                }
              }
            }
          }
        }
      },
      "put": {
        "tags": [
          "LigneravitaillementArticles"
        ],
        "parameters": [
          {
            "name": "id",
            "in": "path",
            "required": true,
            "schema": {
              "type": "integer",
              "format": "int32"
            }
          }
        ],
        "requestBody": {
          "content": {
            "application/json": {
              "schema": {
                "$ref": "#/components/schemas/LigneravitaillementArticle"
              }
            },
            "text/json": {
              "schema": {
                "$ref": "#/components/schemas/LigneravitaillementArticle"
              }
            },
            "application/*+json": {
              "schema": {
                "$ref": "#/components/schemas/LigneravitaillementArticle"
              }
            }
          }
        },
        "responses": {
          "200": {
            "description": "OK"
          }
        }
      },
      "delete": {
        "tags": [
          "LigneravitaillementArticles"
        ],
        "parameters": [
          {
            "name": "id",
            "in": "path",
            "required": true,
            "schema": {
              "type": "integer",
              "format": "int32"
            }
          }
        ],
        "responses": {
          "200": {
            "description": "OK"
          }
        }
      }
    },
    "/api/LigneravitaillementArticles/ravitaillement/{idRavi}": {
      "get": {
        "tags": [
          "LigneravitaillementArticles"
        ],
        "parameters": [
          {
            "name": "idRavi",
            "in": "path",
            "required": true,
            "schema": {
              "type": "integer",
              "format": "int32"
            }
          }
        ],
        "responses": {
          "200": {
            "description": "OK",
            "content": {
              "text/plain": {
                "schema": {
                  "type": "array",
                  "items": {
                    "$ref": "#/components/schemas/LigneravitaillementArticle"
                  }
                }
              },
              "application/json": {
                "schema": {
                  "type": "array",
                  "items": {
                    "$ref": "#/components/schemas/LigneravitaillementArticle"
                  }
                }
              },
              "text/json": {
                "schema": {
                  "type": "array",
                  "items": {
                    "$ref": "#/components/schemas/LigneravitaillementArticle"
                  }
                }
              }
            }
          }
        }
      }
    },
    "/api/LigneravitaillementCommandes": {
      "get": {
        "tags": [
          "LigneravitaillementCommandes"
        ],
        "responses": {
          "200": {
            "description": "OK",
            "content": {
              "text/plain": {
                "schema": {
                  "type": "array",
                  "items": {
                    "$ref": "#/components/schemas/LigneravitaillementCommande"
                  }
                }
              },
              "application/json": {
                "schema": {
                  "type": "array",
                  "items": {
                    "$ref": "#/components/schemas/LigneravitaillementCommande"
                  }
                }
              },
              "text/json": {
                "schema": {
                  "type": "array",
                  "items": {
                    "$ref": "#/components/schemas/LigneravitaillementCommande"
                  }
                }
              }
            }
          }
        }
      },
      "post": {
        "tags": [
          "LigneravitaillementCommandes"
        ],
        "requestBody": {
          "content": {
            "application/json": {
              "schema": {
                "$ref": "#/components/schemas/LigneravitaillementCommande"
              }
            },
            "text/json": {
              "schema": {
                "$ref": "#/components/schemas/LigneravitaillementCommande"
              }
            },
            "application/*+json": {
              "schema": {
                "$ref": "#/components/schemas/LigneravitaillementCommande"
              }
            }
          }
        },
        "responses": {
          "200": {
            "description": "OK",
            "content": {
              "text/plain": {
                "schema": {
                  "$ref": "#/components/schemas/LigneravitaillementCommande"
                }
              },
              "application/json": {
                "schema": {
                  "$ref": "#/components/schemas/LigneravitaillementCommande"
                }
              },
              "text/json": {
                "schema": {
                  "$ref": "#/components/schemas/LigneravitaillementCommande"
                }
              }
            }
          }
        }
      }
    },
    "/api/LigneravitaillementCommandes/{id}": {
      "get": {
        "tags": [
          "LigneravitaillementCommandes"
        ],
        "parameters": [
          {
            "name": "id",
            "in": "path",
            "required": true,
            "schema": {
              "type": "integer",
              "format": "int32"
            }
          }
        ],
        "responses": {
          "200": {
            "description": "OK",
            "content": {
              "text/plain": {
                "schema": {
                  "$ref": "#/components/schemas/LigneravitaillementCommande"
                }
              },
              "application/json": {
                "schema": {
                  "$ref": "#/components/schemas/LigneravitaillementCommande"
                }
              },
              "text/json": {
                "schema": {
                  "$ref": "#/components/schemas/LigneravitaillementCommande"
                }
              }
            }
          }
        }
      },
      "put": {
        "tags": [
          "LigneravitaillementCommandes"
        ],
        "parameters": [
          {
            "name": "id",
            "in": "path",
            "required": true,
            "schema": {
              "type": "integer",
              "format": "int32"
            }
          }
        ],
        "requestBody": {
          "content": {
            "application/json": {
              "schema": {
                "$ref": "#/components/schemas/LigneravitaillementCommande"
              }
            },
            "text/json": {
              "schema": {
                "$ref": "#/components/schemas/LigneravitaillementCommande"
              }
            },
            "application/*+json": {
              "schema": {
                "$ref": "#/components/schemas/LigneravitaillementCommande"
              }
            }
          }
        },
        "responses": {
          "200": {
            "description": "OK"
          }
        }
      },
      "delete": {
        "tags": [
          "LigneravitaillementCommandes"
        ],
        "parameters": [
          {
            "name": "id",
            "in": "path",
            "required": true,
            "schema": {
              "type": "integer",
              "format": "int32"
            }
          }
        ],
        "responses": {
          "200": {
            "description": "OK"
          }
        }
      }
    },
    "/api/LigneravitaillementCommandes/ravitaillement/{idRavi}": {
      "get": {
        "tags": [
          "LigneravitaillementCommandes"
        ],
        "parameters": [
          {
            "name": "idRavi",
            "in": "path",
            "required": true,
            "schema": {
              "type": "integer",
              "format": "int32"
            }
          }
        ],
        "responses": {
          "200": {
            "description": "OK",
            "content": {
              "text/plain": {
                "schema": {
                  "type": "array",
                  "items": {
                    "$ref": "#/components/schemas/LigneravitaillementCommande"
                  }
                }
              },
              "application/json": {
                "schema": {
                  "type": "array",
                  "items": {
                    "$ref": "#/components/schemas/LigneravitaillementCommande"
                  }
                }
              },
              "text/json": {
                "schema": {
                  "type": "array",
                  "items": {
                    "$ref": "#/components/schemas/LigneravitaillementCommande"
                  }
                }
              }
            }
          }
        }
      }
    },
    "/api/LigneravitaillementCommandes/commande/{idCommande}": {
      "get": {
        "tags": [
          "LigneravitaillementCommandes"
        ],
        "parameters": [
          {
            "name": "idCommande",
            "in": "path",
            "required": true,
            "schema": {
              "type": "integer",
              "format": "int32"
            }
          }
        ],
        "responses": {
          "200": {
            "description": "OK",
            "content": {
              "text/plain": {
                "schema": {
                  "type": "array",
                  "items": {
                    "$ref": "#/components/schemas/LigneravitaillementCommande"
                  }
                }
              },
              "application/json": {
                "schema": {
                  "type": "array",
                  "items": {
                    "$ref": "#/components/schemas/LigneravitaillementCommande"
                  }
                }
              },
              "text/json": {
                "schema": {
                  "type": "array",
                  "items": {
                    "$ref": "#/components/schemas/LigneravitaillementCommande"
                  }
                }
              }
            }
          }
        }
      }
    },
    "/api/Ligneravitaillements": {
      "get": {
        "tags": [
          "Ligneravitaillements"
        ],
        "responses": {
          "200": {
            "description": "OK",
            "content": {
              "text/plain": {
                "schema": {
                  "type": "array",
                  "items": {
                    "$ref": "#/components/schemas/Ligneravitaillement"
                  }
                }
              },
              "application/json": {
                "schema": {
                  "type": "array",
                  "items": {
                    "$ref": "#/components/schemas/Ligneravitaillement"
                  }
                }
              },
              "text/json": {
                "schema": {
                  "type": "array",
                  "items": {
                    "$ref": "#/components/schemas/Ligneravitaillement"
                  }
                }
              }
            }
          }
        }
      },
      "post": {
        "tags": [
          "Ligneravitaillements"
        ],
        "requestBody": {
          "content": {
            "application/json": {
              "schema": {
                "$ref": "#/components/schemas/Ligneravitaillement"
              }
            },
            "text/json": {
              "schema": {
                "$ref": "#/components/schemas/Ligneravitaillement"
              }
            },
            "application/*+json": {
              "schema": {
                "$ref": "#/components/schemas/Ligneravitaillement"
              }
            }
          }
        },
        "responses": {
          "200": {
            "description": "OK",
            "content": {
              "text/plain": {
                "schema": {
                  "$ref": "#/components/schemas/Ligneravitaillement"
                }
              },
              "application/json": {
                "schema": {
                  "$ref": "#/components/schemas/Ligneravitaillement"
                }
              },
              "text/json": {
                "schema": {
                  "$ref": "#/components/schemas/Ligneravitaillement"
                }
              }
            }
          }
        }
      }
    },
    "/api/Ligneravitaillements/{id}": {
      "get": {
        "tags": [
          "Ligneravitaillements"
        ],
        "parameters": [
          {
            "name": "id",
            "in": "path",
            "required": true,
            "schema": {
              "type": "integer",
              "format": "int32"
            }
          }
        ],
        "responses": {
          "200": {
            "description": "OK",
            "content": {
              "text/plain": {
                "schema": {
                  "$ref": "#/components/schemas/Ligneravitaillement"
                }
              },
              "application/json": {
                "schema": {
                  "$ref": "#/components/schemas/Ligneravitaillement"
                }
              },
              "text/json": {
                "schema": {
                  "$ref": "#/components/schemas/Ligneravitaillement"
                }
              }
            }
          }
        }
      },
      "put": {
        "tags": [
          "Ligneravitaillements"
        ],
        "parameters": [
          {
            "name": "id",
            "in": "path",
            "required": true,
            "schema": {
              "type": "integer",
              "format": "int32"
            }
          }
        ],
        "requestBody": {
          "content": {
            "application/json": {
              "schema": {
                "$ref": "#/components/schemas/Ligneravitaillement"
              }
            },
            "text/json": {
              "schema": {
                "$ref": "#/components/schemas/Ligneravitaillement"
              }
            },
            "application/*+json": {
              "schema": {
                "$ref": "#/components/schemas/Ligneravitaillement"
              }
            }
          }
        },
        "responses": {
          "200": {
            "description": "OK"
          }
        }
      },
      "delete": {
        "tags": [
          "Ligneravitaillements"
        ],
        "parameters": [
          {
            "name": "id",
            "in": "path",
            "required": true,
            "schema": {
              "type": "integer",
              "format": "int32"
            }
          }
        ],
        "responses": {
          "200": {
            "description": "OK"
          }
        }
      }
    },
    "/api/Ligneravitaillements/client/{idClient}": {
      "get": {
        "tags": [
          "Ligneravitaillements"
        ],
        "parameters": [
          {
            "name": "idClient",
            "in": "path",
            "required": true,
            "schema": {
              "type": "integer",
              "format": "int32"
            }
          }
        ],
        "responses": {
          "200": {
            "description": "OK",
            "content": {
              "text/plain": {
                "schema": {
                  "type": "array",
                  "items": {
                    "$ref": "#/components/schemas/Ligneravitaillement"
                  }
                }
              },
              "application/json": {
                "schema": {
                  "type": "array",
                  "items": {
                    "$ref": "#/components/schemas/Ligneravitaillement"
                  }
                }
              },
              "text/json": {
                "schema": {
                  "type": "array",
                  "items": {
                    "$ref": "#/components/schemas/Ligneravitaillement"
                  }
                }
              }
            }
          }
        }
      }
    }
  },
  "components": {
    "schemas": {
      "Article": {
        "type": "object",
        "properties": {
          "idArticle": {
            "type": "integer",
            "format": "int32"
          },
          "nomArticle": {
            "type": "string",
            "nullable": true
          },
          "ligneravitaillementArticles": {
            "type": "array",
            "items": {
              "$ref": "#/components/schemas/LigneravitaillementArticle"
            },
            "nullable": true
          }
        },
        "additionalProperties": false
      },
      "Client": {
        "type": "object",
        "properties": {
          "idClient": {
            "type": "integer",
            "format": "int32"
          },
          "nom": {
            "type": "string",
            "nullable": true
          },
          "adresse": {
            "type": "string",
            "nullable": true
          },
          "email": {
            "type": "string",
            "nullable": true
          },
          "telephone": {
            "type": "string",
            "nullable": true
          },
          "societe": {
            "type": "string",
            "nullable": true
          },
          "ville": {
            "type": "string",
            "nullable": true
          },
          "commandes": {
            "type": "array",
            "items": {
              "$ref": "#/components/schemas/Commande"
            },
            "nullable": true
          },
          "ligneravitaillements": {
            "type": "array",
            "items": {
              "$ref": "#/components/schemas/Ligneravitaillement"
            },
            "nullable": true
          }
        },
        "additionalProperties": false
      },
      "Commande": {
        "type": "object",
        "properties": {
          "idCommande": {
            "type": "integer",
            "format": "int32"
          },
          "dateCommande": {
            "type": "string",
            "format": "date-time"
          },
          "libelle": {
            "type": "string",
            "nullable": true
          },
          "montant": {
            "type": "number",
            "format": "double"
          },
          "idClient": {
            "type": "integer",
            "format": "int32"
          },
          "client": {
            "$ref": "#/components/schemas/Client"
          },
          "details": {
            "type": "array",
            "items": {
              "$ref": "#/components/schemas/Detail"
            },
            "nullable": true
          },
          "ligneravitaillementCommandes": {
            "type": "array",
            "items": {
              "$ref": "#/components/schemas/LigneravitaillementCommande"
            },
            "nullable": true
          }
        },
        "additionalProperties": false
      },
      "Detail": {
        "type": "object",
        "properties": {
          "idDetail": {
            "type": "integer",
            "format": "int32"
          },
          "quantiteArticle": {
            "type": "integer",
            "format": "int32"
          },
          "prix": {
            "type": "number",
            "format": "double"
          },
          "idCommande": {
            "type": "integer",
            "format": "int32"
          },
          "commande": {
            "$ref": "#/components/schemas/Commande"
          }
        },
        "additionalProperties": false
      },
      "Ligneravitaillement": {
        "type": "object",
        "properties": {
          "idRavi": {
            "type": "integer",
            "format": "int32"
          },
          "code": {
            "type": "string",
            "nullable": true
          },
          "idClient": {
            "type": "integer",
            "format": "int32"
          },
          "client": {
            "$ref": "#/components/schemas/Client"
          },
          "ligneravitaillementArticles": {
            "type": "array",
            "items": {
              "$ref": "#/components/schemas/LigneravitaillementArticle"
            },
            "nullable": true
          },
          "ligneravitaillementCommandes": {
            "type": "array",
            "items": {
              "$ref": "#/components/schemas/LigneravitaillementCommande"
            },
            "nullable": true
          }
        },
        "additionalProperties": false
      },
      "LigneravitaillementArticle": {
        "type": "object",
        "properties": {
          "idRaviArticle": {
            "type": "integer",
            "format": "int32"
          },
          "prixUnitaire": {
            "type": "number",
            "format": "double"
          },
          "idArticle": {
            "type": "integer",
            "format": "int32"
          },
          "quantite": {
            "type": "integer",
            "format": "int32"
          },
          "idRavi": {
            "type": "integer",
            "format": "int32"
          },
          "article": {
            "$ref": "#/components/schemas/Article"
          },
          "ligneravitaillement": {
            "$ref": "#/components/schemas/Ligneravitaillement"
          }
        },
        "additionalProperties": false
      },
      "LigneravitaillementCommande": {
        "type": "object",
        "properties": {
          "idDetail": {
            "type": "integer",
            "format": "int32"
          },
          "idCommande": {
            "type": "integer",
            "format": "int32"
          },
          "idRavi": {
            "type": "integer",
            "format": "int32"
          },
          "dateCreation": {
            "type": "string",
            "format": "date-time"
          },
          "montant": {
            "type": "number",
            "format": "double"
          },
          "commande": {
            "$ref": "#/components/schemas/Commande"
          },
          "ligneravitaillement": {
            "$ref": "#/components/schemas/Ligneravitaillement"
          }
        },
        "additionalProperties": false
      }
    }
  },
  "tags": [
    {
      "name": "Articles"
    },
    {
      "name": "Clients"
    },
    {
      "name": "Commandes"
    },
    {
      "name": "Details"
    },
    {
      "name": "LigneravitaillementArticles"
    },
    {
      "name": "LigneravitaillementCommandes"
    },
    {
      "name": "Ligneravitaillements"
    }
  ]
}